README.md
setup.py
SecAutoBan/__init__.py
SecAutoBan/sec_auto_ban.py
SecAutoBan/util.py
SecAutoBan/websocket_client.py
SecAutoBan.egg-info/PKG-INFO
SecAutoBan.egg-info/SOURCES.txt
SecAutoBan.egg-info/dependency_links.txt
SecAutoBan.egg-info/requires.txt
SecAutoBan.egg-info/top_level.txt