Metadata-Version: 2.4
Name: SecAutoBan
Version: 4.0.2
Summary: SecAutoBan SDK
Home-page: https://github.com/SecAegis/SecAutoBan
Author: SecReport
Author-email: secaegis@outlook.com
Requires-Dist: pycryptodome
Requires-Dist: websocket-client
Requires-Dist: ipaddress
Dynamic: author
Dynamic: author-email
Dynamic: description
Dynamic: description-content-type
Dynamic: home-page
Dynamic: requires-dist
Dynamic: summary
